Workbook
Name Slicer_Category: #N/A
Name Slicer_Region: #N/A
Name Slicer_Salesperson: #N/A

Sheet PivotTable Dashboard
A3: Sum of Revenue | B3: Column Labels
A4: Row Labels | B4: Electronics | C4: Furniture | D4: Office Supplies | E4: Software | F4: Grand Total
A5: Cork | B5: 858105.01 | C5: 421643.45 | D5: 55773.71 | E5: 307504.99 | F5: 1643027.2
A6: Dublin | B6: 997279.82 | C6: 461898.87 | D6: 53092.5 | E6: 228190 | F6: 1740461.2
A7: Galway | B7: 1000567.2 | C7: 534887.34 | D7: 60422.67 | E7: 291742.88 | F7: 1887620.1
A8: Limerick | B8: 890334.97 | C8: 406156 | D8: 63187.34 | E8: 325252.16 | F8: 1684930.5
A9: Waterford | B9: 976956.99 | C9: 526862.35 | D9: 72936.13 | E9: 217773.69 | F9: 1794529.2
A10: Grand Total | B10: 4723244 | C10: 2351448 | D10: 305412.35 | E10: 1370463.7 | F10: 8750568.1

Sheet RawData
A1: OrderID | B1: Date | C1: Region | D1: Category | E1: Product | F1: Salesperson | G1: Units Sold | H1: Unit Price | I1: Unit Cost | J1: Revenue | K1: Cost | L1: Profit
A2: 1518 | B2: 45292 | C2: Cork | D2: Office Supplies | E2: Stapler | F2: Ciara Doyle | G2: 25 | H2: 28.49 | I2: 16.38 | J2: =G2*H2 -> 712.25 | K2: =G2*I2 -> 409.5 | L2: =J2-K2 -> 302.75
A3: 2306 | B3: 45292 | C3: Waterford | D3: Electronics | E3: Keyboard | F3: Niamh Connolly | G3: 5 | H3: 643.75 | I3: 355.55 | J3: =G3*H3 -> 3218.75 | K3: =G3*I3 -> 1777.75 | L3: =J3-K3 -> 1441
A4: 1077 | B4: 45293 | C4: Waterford | D4: Software | E4: Cloud Storage | F4: Aoife Byrne | G4: 13 | H4: 143.77 | I4: 73.74 | J4: =G4*H4 -> 1869.01 | K4: =G4*I4 -> 958.62 | L4: =J4-K4 -> 910.39
A5: 2423 | B5: 45293 | C5: Limerick | D5: Office Supplies | E5: Notebook | F5: Sean Murphy | G5: 20 | H5: 27.22 | I5: 14.97 | J5: =G5*H5 -> 544.4 | K5: =G5*I5 -> 299.4 | L5: =J5-K5 -> 245
A6: 2794 | B6: 45293 | C6: Waterford | D6: Office Supplies | E6: Notebook | F6: Ciara Doyle | G6: 19 | H6: 53 | I6: 37.64 | J6: =G6*H6 -> 1007 | K6: =G6*I6 -> 715.16 | L6: =J6-K6 -> 291.84
A7: 1339 | B7: 45294 | C7: Dublin | D7: Electronics | E7: Laptop | F7: Darragh Ryan | G7: 10 | H7: 857.53 | I7: 622.73 | J7: =G7*H7 -> 8575.3 | K7: =G7*I7 -> 6227.3 | L7: =J7-K7 -> 2348
A8: 1697 | B8: 45294 | C8: Dublin | D8: Furniture | E8: Office Desk | F8: Aoife Byrne | G8: 27 | H8: 270 | I8: 160.47 | J8: =G8*H8 -> 7290 | K8: =G8*I8 -> 4332.69 | L8: =J8-K8 -> 2957.31
A9: 1872 | B9: 45294 | C9: Cork | D9: Office Supplies | E9: Printer Paper | F9: Niamh Connolly | G9: 25 | H9: 48.42 | I9: 25.58 | J9: =G9*H9 -> 1210.5 | K9: =G9*I9 -> 639.5 | L9: =J9-K9 -> 571
A10: 2446 | B10: 45294 | C10: Galway | D10: Office Supplies | E10: Stapler | F10: Ronan Walsh | G10: 22 | H10: 44.26 | I10: 26.31 | J10: =G10*H10 -> 973.72 | K10: =G10*I10 -> 578.82 | L10: =J10-K10 -> 394.9
A11: 2603 | B11: 45294 | C11: Limerick | D11: Software | E11: Office Suite | F11: Sean Murphy | G11: 18 | H11: 298.68 | I11: 208.13 | J11: =G11*H11 -> 5376.24 | K11: =G11*I11 -> 3746.34 | L11: =J11-K11 -> 1629.9
A12: 2637 | B12: 45294 | C12: Dublin | D12: Electronics | E12: Webcam | F12: Sinead Kelly | G12: 30 | H12: 424.54 | I12: 279.28 | J12: =G12*H12 -> 12736.2 | K12: =G12*I12 -> 8378.4 | L12: =J12-K12 -> 4357.8
A13: 1931 | B13: 45296 | C13: Limerick | D13: Furniture | E13: Bookshelf | F13: Sinead Kelly | G13: 3 | H13: 96.43 | I13: 49.89 | J13: =G13*H13 -> 289.29 | K13: =G13*I13 -> 149.67 | L13: =J13-K13 -> 139.62
... A1801: 1890 | B1801: 46021 | C1801: Limerick | D1801: Office Supplies | E1801: Notebook | F1801: Sean Murphy | G1801: 10 | H1801: 59.68 | I1801: 41.27 | J1801: =G1801*H1801 -> 596.8 | K1801: =G1801*I1801 -> 412.7 | L1801: =J1801-K1801 -> 184.1

Sheet Summary
A1: Sales Performance Summary
A3: Total Revenue | B3: =SUM(RawData!J2:J1801) -> 8750568.1 | D3: Revenue by Region | G3: Revenue by Category
A4: Total Cost | B4: =SUM(RawData!K2:K1801) -> 5490849.6 | D4: Region | E4: Revenue | G4: Category | H4: Revenue
A5: Total Profit | B5: =SUM(RawData!L2:L1801) -> 3259718.5 | D5: Dublin | E5: =SUMIFS(RawData!J2:J1801,RawData!C2:C1801,D5) -> 1740461.2 | G5: Electronics | H5: =SUMIFS(RawData!J2:J1801,RawData!D2:D1801,G5) -> 4723244
A6: Total Units Sold | B6: =SUM(RawData!G2:G1801) -> 36246 | D6: Cork | E6: =SUMIFS(RawData!J2:J1801,RawData!C2:C1801,D6) -> 1643027.2 | G6: Office Supplies | H6: =SUMIFS(RawData!J2:J1801,RawData!D2:D1801,G6) -> 305412.35
A7: Avg Order Value | B7: =AVERAGE(RawData!J2:J1801) -> 4861.4267 | D7: Galway | E7: =SUMIFS(RawData!J2:J1801,RawData!C2:C1801,D7) -> 1887620.1 | G7: Furniture | H7: =SUMIFS(RawData!J2:J1801,RawData!D2:D1801,G7) -> 2351448
D8: Limerick | E8: =SUMIFS(RawData!J2:J1801,RawData!C2:C1801,D8) -> 1684930.5 | G8: Software | H8: =SUMIFS(RawData!J2:J1801,RawData!D2:D1801,G8) -> 1370463.7
D9: Waterford | E9: =SUMIFS(RawData!J2:J1801,RawData!C2:C1801,D9) -> 1794529.2
A10: Monthly Revenue Trend
A11: Month | B11: Revenue
A12: 45292 | B12: =SUMIFS(RawData!J2:J1801,RawData!B2:B1801,">="&A12,RawData!B2:B1801,"<"&DATE(2024,2,1)) -> 306407.09
A13: 45323 | B13: =SUMIFS(RawData!J2:J1801,RawData!B2:B1801,">="&A13,RawData!B2:B1801,"<"&DATE(2024,3,1)) -> 320074.03
A14: 45352 | B14: =SUMIFS(RawData!J2:J1801,RawData!B2:B1801,">="&A14,RawData!B2:B1801,"<"&DATE(2024,4,1)) -> 364245
A15: 45383 | B15: =SUMIFS(RawData!J2:J1801,RawData!B2:B1801,">="&A15,RawData!B2:B1801,"<"&DATE(2024,5,1)) -> 330352.21
A16: 45413 | B16: =SUMIFS(RawData!J2:J1801,RawData!B2:B1801,">="&A16,RawData!B2:B1801,"<"&DATE(2024,6,1)) -> 426742.24
A17: 45444 | B17: =SUMIFS(RawData!J2:J1801,RawData!B2:B1801,">="&A17,RawData!B2:B1801,"<"&DATE(2024,7,1)) -> 288886.42
A18: 45474 | B18: =SUMIFS(RawData!J2:J1801,RawData!B2:B1801,">="&A18,RawData!B2:B1801,"<"&DATE(2024,8,1)) -> 345366.98
A19: 45505 | B19: =SUMIFS(RawData!J2:J1801,RawData!B2:B1801,">="&A19,RawData!B2:B1801,"<"&DATE(2024,9,1)) -> 351174.53
A20: 45536 | B20: =SUMIFS(RawData!J2:J1801,RawData!B2:B1801,">="&A20,RawData!B2:B1801,"<"&DATE(2024,10,1)) -> 318550.88
A21: 45566 | B21: =SUMIFS(RawData!J2:J1801,RawData!B2:B1801,">="&A21,RawData!B2:B1801,"<"&DATE(2024,11,1)) -> 389142.62
A22: 45597 | B22: =SUMIFS(RawData!J2:J1801,RawData!B2:B1801,">="&A22,RawData!B2:B1801,"<"&DATE(2024,12,1)) -> 301129.51
A23: 45627 | B23: =SUMIFS(RawData!J2:J1801,RawData!B2:B1801,">="&A23,RawData!B2:B1801,"<"&DATE(2025,1,1)) -> 300540.5
A24: 45658 | B24: =SUMIFS(RawData!J2:J1801,RawData!B2:B1801,">="&A24,RawData!B2:B1801,"<"&DATE(2025,2,1)) -> 330304.39
A25: 45689 | B25: =SUMIFS(RawData!J2:J1801,RawData!B2:B1801,">="&A25,RawData!B2:B1801,"<"&DATE(2025,3,1)) -> 388389.91
A26: 45717 | B26: =SUMIFS(RawData!J2:J1801,RawData!B2:B1801,">="&A26,RawData!B2:B1801,"<"&DATE(2025,4,1)) -> 340423.4
A27: 45748 | B27: =SUMIFS(RawData!J2:J1801,RawData!B2:B1801,">="&A27,RawData!B2:B1801,"<"&DATE(2025,5,1)) -> 298092.51
A28: 45778 | B28: =SUMIFS(RawData!J2:J1801,RawData!B2:B1801,">="&A28,RawData!B2:B1801,"<"&DATE(2025,6,1)) -> 305462.26
A29: 45809 | B29: =SUMIFS(RawData!J2:J1801,RawData!B2:B1801,">="&A29,RawData!B2:B1801,"<"&DATE(2025,7,1)) -> 455287.67
A30: 45839 | B30: =SUMIFS(RawData!J2:J1801,RawData!B2:B1801,">="&A30,RawData!B2:B1801,"<"&DATE(2025,8,1)) -> 528540.75
A31: 45870 | B31: =SUMIFS(RawData!J2:J1801,RawData!B2:B1801,">="&A31,RawData!B2:B1801,"<"&DATE(2025,9,1)) -> 441181.81
A32: 45901 | B32: =SUMIFS(RawData!J2:J1801,RawData!B2:B1801,">="&A32,RawData!B2:B1801,"<"&DATE(2025,10,1)) -> 384406.53
A33: 45931 | B33: =SUMIFS(RawData!J2:J1801,RawData!B2:B1801,">="&A33,RawData!B2:B1801,"<"&DATE(2025,11,1)) -> 513375.26
A34: 45962 | B34: =SUMIFS(RawData!J2:J1801,RawData!B2:B1801,">="&A34,RawData!B2:B1801,"<"&DATE(2025,12,1)) -> 357682.19
A35: 45992 | B35: =SUMIFS(RawData!J2:J1801,RawData!B2:B1801,">="&A35,RawData!B2:B1801,"<"&DATE(2026,1,1)) -> 364809.4
